wxalerts/__init__.py
wxalerts/wxalerts.py
wxalerts-0.0.3.dist-info/LICENSE
wxalerts-0.0.3.dist-info/METADATA
wxalerts-0.0.3.dist-info/WHEEL
wxalerts-0.0.3.dist-info/top_level.txt
wxalerts-0.0.3.dist-info/RECORD
